README.txt
inventory.py
setup.py
square_cli.egg-info/PKG-INFO
square_cli.egg-info/SOURCES.txt
square_cli.egg-info/dependency_links.txt
square_cli.egg-info/requires.txt
square_cli.egg-info/top_level.txt