Metadata-Version: 1.0
Name: square-cli
Version: 1.1.1
Summary: This is a CLI for square project
Home-page: http://gerrit.mirantis.com/a/mos-scale/square
Author: MOS team
Author-email: mos-scale@mirantis.com
License: BSD
Platform: UNKNOWN
